[{
  "_id": {
    "$oid": "65f2a1b1c2d3e4f5a6b7c8d1"
  },
  "name": "Áo Dài & Cổ Phục",
  "slug": "ao-dai-va-co-phuc",
  "parentId": null,
  "description": "Các loại áo dài truyền thống, cách tân và trang phục cổ phong Việt Nam, Trung Hoa"
},
{
  "_id": {
    "$oid": "65f2a1b1c2d3e4f5a6b7c8d2"
  },
  "name": "Váy Dạ Hội & Váy Cưới",
  "slug": "vay-da-hoi-va-vay-cuoi",
  "parentId": null,
  "description": "Đầm dạ tiệc cao cấp, váy cưới cô dâu, váy chụp ảnh sự kiện"
},
{
  "_id": {
    "$oid": "65f2a1b1c2d3e4f5a6b7c8d3"
  },
  "name": "Trang Phục Concept / Chụp Ảnh",
  "slug": "trang-phuc-concept-chup-anh",
  "parentId": null,
  "description": "Đầm nàng thơ, váy loli, cosplay, trang phục ngoại cảnh"
},
{
  "_id": {
    "$oid": "65f2a1b1c2d3e4f5a6b7c8d4"
  },
  "name": "Áo Dài Cách Tân",
  "slug": "ao-dai-cach-tan",
  "parentId": {
    "$oid": "65f2a1b1c2d3e4f5a6b7c8d1"
  },
  "description": "Áo dài phom dáng hiện đại, trẻ trung cho các dịp lễ tết, chụp ảnh"
},
{
  "_id": {
    "$oid": "65f2a1b1c2d3e4f5a6b7c8d5"
  },
  "name": "Váy Dạ Hội Cao Cấp",
  "slug": "vay-da-hoi-cao-cap",
  "parentId": {
    "$oid": "65f2a1b1c2d3e4f5a6b7c8d2"
  },
  "description": "Đầm dạ tiệc dáng dài, đầm đính đá, kim sa lấp lánh"
},
{
  "_id": {
    "$oid": "65f2a1b1c2d3e4f5a6b7c8d6"
  },
  "name": "Váy Nàng Thơ (Vintage/Boho)",
  "slug": "vay-nang-tho-vintage-boho",
  "parentId": {
    "$oid": "65f2a1b1c2d3e4f5a6b7c8d3"
  },
  "description": "Váy trắng voan bồng bềnh, phong cách nhẹ nhàng đi biển hoặc chụp ngoại cảnh"
},
{
  "_id": {
    "$oid": "6a1d9001bfc8b78a8a813ed9"
  },
  "name": "Đồ du lịch",
  "description": "Trang phục dành cho các chuyến đi chơi, khám phá.",
  "parentId": null,
  "isActive": true,
  "createdAt": {
    "$date": "2026-06-01T13:58:25.711Z"
  },
  "updatedAt": {
    "$date": "2026-06-01T13:58:25.711Z"
  },
  "__v": 0
},
{
  "_id": {
    "$oid": "6a1d9001bfc8b78a8a813eda"
  },
  "name": "Đi biển",
  "description": "Danh mục con của Đồ du lịch",
  "parentId": {
    "$oid": "6a1d9001bfc8b78a8a813ed9"
  },
  "isActive": true,
  "createdAt": {
    "$date": "2026-06-01T13:58:25.769Z"
  },
  "updatedAt": {
    "$date": "2026-06-01T13:58:25.769Z"
  },
  "__v": 0
},
{
  "_id": {
    "$oid": "6a1d9001bfc8b78a8a813edb"
  },
  "name": "Leo núi",
  "description": "Danh mục con của Đồ du lịch",
  "parentId": {
    "$oid": "6a1d9001bfc8b78a8a813ed9"
  },
  "isActive": true,
  "createdAt": {
    "$date": "2026-06-01T13:58:25.824Z"
  },
  "updatedAt": {
    "$date": "2026-06-01T13:58:25.824Z"
  },
  "__v": 0
},
{
  "_id": {
    "$oid": "6a1d9001bfc8b78a8a813edc"
  },
  "name": "Dã ngoại",
  "description": "Danh mục con của Đồ du lịch",
  "parentId": {
    "$oid": "6a1d9001bfc8b78a8a813ed9"
  },
  "isActive": true,
  "createdAt": {
    "$date": "2026-06-01T13:58:25.872Z"
  },
  "updatedAt": {
    "$date": "2026-06-01T13:58:25.872Z"
  },
  "__v": 0
},
{
  "_id": {
    "$oid": "6a1d9001bfc8b78a8a813edd"
  },
  "name": "Áo dài nữ",
  "description": "Bộ sưu tập áo dài truyền thống và hiện đại.",
  "parentId": null,
  "isActive": true,
  "createdAt": {
    "$date": "2026-06-01T13:58:25.927Z"
  },
  "updatedAt": {
    "$date": "2026-06-01T13:58:25.927Z"
  },
  "__v": 0
},
{
  "_id": {
    "$oid": "6a1d9001bfc8b78a8a813ede"
  },
  "name": "Áo dài truyền thống",
  "description": "Danh mục con của Áo dài nữ",
  "parentId": {
    "$oid": "6a1d9001bfc8b78a8a813edd"
  },
  "isActive": true,
  "createdAt": {
    "$date": "2026-06-01T13:58:25.978Z"
  },
  "updatedAt": {
    "$date": "2026-06-01T13:58:25.978Z"
  },
  "__v": 0
},
{
  "_id": {
    "$oid": "6a1d9002bfc8b78a8a813edf"
  },
  "name": "Áo dài cách tân",
  "description": "Danh mục con của Áo dài nữ",
  "parentId": {
    "$oid": "6a1d9001bfc8b78a8a813edd"
  },
  "isActive": true,
  "createdAt": {
    "$date": "2026-06-01T13:58:26.032Z"
  },
  "updatedAt": {
    "$date": "2026-06-01T13:58:26.032Z"
  },
  "__v": 0
},
{
  "_id": {
    "$oid": "6a1d9002bfc8b78a8a813ee0"
  },
  "name": "Áo dài cưới",
  "description": "Danh mục con của Áo dài nữ",
  "parentId": {
    "$oid": "6a1d9001bfc8b78a8a813edd"
  },
  "isActive": true,
  "createdAt": {
    "$date": "2026-06-01T13:58:26.082Z"
  },
  "updatedAt": {
    "$date": "2026-06-01T13:58:26.082Z"
  },
  "__v": 0
},
{
  "_id": {
    "$oid": "6a1d9002bfc8b78a8a813ee1"
  },
  "name": "Váy tiệc",
  "description": "Trang phục dự tiệc sang trọng, lộng lẫy.",
  "parentId": null,
  "isActive": true,
  "createdAt": {
    "$date": "2026-06-01T13:58:26.149Z"
  },
  "updatedAt": {
    "$date": "2026-06-01T13:58:26.149Z"
  },
  "__v": 0
},
{
  "_id": {
    "$oid": "6a1d9002bfc8b78a8a813ee2"
  },
  "name": "Váy dạ hội",
  "description": "Danh mục con của Váy tiệc",
  "parentId": {
    "$oid": "6a1d9002bfc8b78a8a813ee1"
  },
  "isActive": true,
  "createdAt": {
    "$date": "2026-06-01T13:58:26.201Z"
  },
  "updatedAt": {
    "$date": "2026-06-01T13:58:26.201Z"
  },
  "__v": 0
},
{
  "_id": {
    "$oid": "6a1d9002bfc8b78a8a813ee3"
  },
  "name": "Váy cocktail",
  "description": "Danh mục con của Váy tiệc",
  "parentId": {
    "$oid": "6a1d9002bfc8b78a8a813ee1"
  },
  "isActive": true,
  "createdAt": {
    "$date": "2026-06-01T13:58:26.249Z"
  },
  "updatedAt": {
    "$date": "2026-06-01T13:58:26.249Z"
  },
  "__v": 0
},
{
  "_id": {
    "$oid": "6a1d9002bfc8b78a8a813ee4"
  },
  "name": "Váy công chúa",
  "description": "Danh mục con của Váy tiệc",
  "parentId": {
    "$oid": "6a1d9002bfc8b78a8a813ee1"
  },
  "isActive": true,
  "createdAt": {
    "$date": "2026-06-01T13:58:26.304Z"
  },
  "updatedAt": {
    "$date": "2026-06-01T13:58:26.304Z"
  },
  "__v": 0
},
{
  "_id": {
    "$oid": "6a1d9002bfc8b78a8a813ee5"
  },
  "name": "Set nữ",
  "description": "Các set đồ bộ thời trang, tiện lợi.",
  "parentId": null,
  "isActive": true,
  "createdAt": {
    "$date": "2026-06-01T13:58:26.412Z"
  },
  "updatedAt": {
    "$date": "2026-06-01T13:58:26.412Z"
  },
  "__v": 0
},
{
  "_id": {
    "$oid": "6a1d9002bfc8b78a8a813ee6"
  },
  "name": "Set đồ công sở",
  "description": "Danh mục con của Set nữ",
  "parentId": {
    "$oid": "6a1d9002bfc8b78a8a813ee5"
  },
  "isActive": true,
  "createdAt": {
    "$date": "2026-06-01T13:58:26.508Z"
  },
  "updatedAt": {
    "$date": "2026-06-01T13:58:26.508Z"
  },
  "__v": 0
},
{
  "_id": {
    "$oid": "6a1d9002bfc8b78a8a813ee7"
  },
  "name": "Set dạo phố",
  "description": "Danh mục con của Set nữ",
  "parentId": {
    "$oid": "6a1d9002bfc8b78a8a813ee5"
  },
  "isActive": true,
  "createdAt": {
    "$date": "2026-06-01T13:58:26.572Z"
  },
  "updatedAt": {
    "$date": "2026-06-01T13:58:26.572Z"
  },
  "__v": 0
},
{
  "_id": {
    "$oid": "6a1d9002bfc8b78a8a813ee8"
  },
  "name": "Trang phục nghi lễ",
  "description": "Trang phục cho các dịp lễ nghi trọng đại.",
  "parentId": null,
  "isActive": true,
  "createdAt": {
    "$date": "2026-06-01T13:58:26.635Z"
  },
  "updatedAt": {
    "$date": "2026-06-01T13:58:26.635Z"
  },
  "__v": 0
},
{
  "_id": {
    "$oid": "6a1d9002bfc8b78a8a813ee9"
  },
  "name": "Đồ tốt nghiệp",
  "description": "Danh mục con của Trang phục nghi lễ",
  "parentId": {
    "$oid": "6a1d9002bfc8b78a8a813ee8"
  },
  "isActive": true,
  "createdAt": {
    "$date": "2026-06-01T13:58:26.688Z"
  },
  "updatedAt": {
    "$date": "2026-06-01T13:58:26.688Z"
  },
  "__v": 0
},
{
  "_id": {
    "$oid": "6a1d9002bfc8b78a8a813eea"
  },
  "name": "Cổ phục Việt Nam",
  "description": "Danh mục con của Trang phục nghi lễ",
  "parentId": {
    "$oid": "6a1d9002bfc8b78a8a813ee8"
  },
  "isActive": true,
  "createdAt": {
    "$date": "2026-06-01T13:58:26.757Z"
  },
  "updatedAt": {
    "$date": "2026-06-01T13:58:26.757Z"
  },
  "__v": 0
},
{
  "_id": {
    "$oid": "6a1d91cff4de7aab4bafaaa9"
  },
  "name": "Váy cưới kim cương",
  "description": "Chất liệu quý hiếm",
  "parentId": {
    "$oid": "65f2a1b1c2d3e4f5a6b7c8d2"
  },
  "isActive": true,
  "createdAt": {
    "$date": "2026-06-01T14:06:07.467Z"
  },
  "updatedAt": {
    "$date": "2026-06-01T14:06:12.259Z"
  },
  "__v": 0
}]